meowspeak/__init__.py
meowspeak/meowspeak.py
meowspeak-1.0.3.dist-info/LICENSE
meowspeak-1.0.3.dist-info/METADATA
meowspeak-1.0.3.dist-info/WHEEL
meowspeak-1.0.3.dist-info/entry_points.txt
meowspeak-1.0.3.dist-info/top_level.txt
meowspeak-1.0.3.dist-info/RECORD
