Metadata-Version: 2.1
Name: meowspeak
Version: 1.0.3
Summary: Displays a message 'spoken' by an ASCII cat
Author-email: Kovács Bálint-Hunor <kovacsbalinthunor53@gmail.com>
Project-URL: Homepage, https://github.com/MemerGamer/meowspeak/
Project-URL: Issues, https://github.com/MemerGamer/meowspeak/issues
Classifier: Programming Language :: Python :: 3
Classifier: License :: OSI Approved :: GNU General Public License v3 (GPLv3)
Classifier: Operating System :: OS Independent
Requires-Python: >=3.9
License-File: LICENSE
